Metadata-Version: 2.1
Name: cdep-package-a
Version: 0.0.2
Summary: Package A of cdep
Home-page: UNKNOWN
Author: John Doe
Author-email: jmartinpe@sia.es
License: UNLICENSED
Platform: UNKNOWN
Classifier: Programming Language :: Python :: 3
